nextstephr/__main__.py
nextstephr-0.1.0.dist-info/METADATA
nextstephr-0.1.0.dist-info/WHEEL
nextstephr-0.1.0.dist-info/entry_points.txt
nextstephr-0.1.0.dist-info/top_level.txt
nextstephr-0.1.0.dist-info/RECORD
